kaas_admin/Custome_File_Templates_forCreate.json
kaas_admin/Custome_File_Templates_forPrivacyScan.json
kaas_admin/Custome_File_Templates_forUnittest.json
kaas_admin/Custome_File_Templates_forValidate.json
kaas_admin/__init__.py
kaas_admin/__main__.py
kaas_admin-0.3.2.dist-info/METADATA
kaas_admin-0.3.2.dist-info/WHEEL
kaas_admin-0.3.2.dist-info/entry_points.txt
kaas_admin-0.3.2.dist-info/top_level.txt
kaas_admin-0.3.2.dist-info/RECORD
